{
  "unpublishedPage": {
    "name": "广德洪山",
    "slug": "",
    "layouts": [
      {
        "viewMode": false,
        "dsl": {
          "widgetName": "MainContainer",
          "backgroundColor": "none",
          "rightColumn": 1174,
          "snapColumns": 64,
          "detachFromLayout": true,
          "widgetId": "0",
          "topRow": 0,
          "bottomRow": 560,
          "containerStyle": "none",
          "snapRows": 125,
          "parentRowSpace": 1,
          "type": "CANVAS_WIDGET",
          "canExtend": true,
          "version": 87,
          "minHeight": 890,
          "parentColumnSpace": 1,
          "dynamicTriggerPathList": [],
          "dynamicBindingPathList": [],
          "leftColumn": 0
        },
        "layoutOnLoadActions": [
          [
            {
              "id": "广德洪山_SelectQuery",
              "name": "SelectQuery",
              "confirmBeforeExecute": false,
              "pluginType": "DB",
              "jsonPathKeys": [
                "Table1.sortOrder.order || \"ASC\"",
                "(Table1.pageNo - 1) * Table1.pageSize",
                "Table1.sortOrder.column || 'id'",
                "Table1.pageSize",
                "'广德洪山' || \"\""
              ],
              "timeoutInMillisecond": 10000
            }
          ]
        ],
        "layoutOnLoadActionErrors": [],
        "validOnPageLoadActions": true,
        "id": "广德洪山",
        "deleted": false,
        "policies": [],
        "userPermissions": []
      }
    ],
    "userPermissions": [],
    "policies": [],
    "isHidden": false
  },
  "deleted": false,
  "gitSyncId": "6722f78fbe536311091686fb_6733083fbe53631109168829"
}